MetaAssemblieImprove/Main.py
MetaAssemblieImprove/__init__.py
MetaAssemblieImprove/gapfiller.py
MetaAssemblieImprove/scaffolder.py
MetaAssemblieImprove/version
MetaAssemblieImprove/version.py
MetaAssemblyImprove/Main.py
MetaAssemblyImprove/__init__.py
MetaAssemblyImprove/gapfiller.py
MetaAssemblyImprove/scaffolder.py
MetaAssemblyImprove/version
MetaAssemblyImprove/version.py
MetaAssemblyImprove-0.0.1.data/scripts/MetaAssemblieImprove
MetaAssemblyImprove-0.0.1.data/scripts/MetaAssemblyImprove
MetaAssemblyImprove-0.0.1.dist-info/LICENSE
MetaAssemblyImprove-0.0.1.dist-info/METADATA
MetaAssemblyImprove-0.0.1.dist-info/WHEEL
MetaAssemblyImprove-0.0.1.dist-info/top_level.txt
MetaAssemblyImprove-0.0.1.dist-info/RECORD
